.gitignore
.pre-commit-config.yaml
LICENSE
Makefile
README.md
download-data.sh
pyproject.toml
setup.cfg
setup.py
.github/workflows/pre-commit.yml
.github/workflows/publish.yml
.github/workflows/test.yml
/home/runner/work/starfit/starfit/src/starfit/fitness/abu_data.f90
/home/runner/work/starfit/starfit/src/starfit/fitness/fitting.f90
/home/runner/work/starfit/starfit/src/starfit/fitness/linalg.f90
/home/runner/work/starfit/starfit/src/starfit/fitness/norm.f90
/home/runner/work/starfit/starfit/src/starfit/fitness/powell.f90
/home/runner/work/starfit/starfit/src/starfit/fitness/solver.f90
/home/runner/work/starfit/starfit/src/starfit/fitness/star_data.f90
/home/runner/work/starfit/starfit/src/starfit/fitness/typedef.f90
/home/runner/work/starfit/starfit/src/starfit/fitness/utils.f90
/home/runner/work/starfit/starfit/src/starfit/solgen/solgen.f90
src/starfit/__init__.py
src/starfit/direct.py
src/starfit/fit.py
src/starfit/ga.py
src/starfit/multi.py
src/starfit/single.py
src/starfit/star.py
src/starfit/starfit.py
src/starfit/starplot.py
src/starfit/utils.py
src/starfit.egg-info/PKG-INFO
src/starfit.egg-info/SOURCES.txt
src/starfit.egg-info/dependency_links.txt
src/starfit.egg-info/not-zip-safe
src/starfit.egg-info/requires.txt
src/starfit.egg-info/top_level.txt
src/starfit/autils/.gitignore
src/starfit/autils/__init__.py
src/starfit/autils/abumodel.py
src/starfit/autils/abuset.py
src/starfit/autils/abusets.py
src/starfit/autils/isotope.py
src/starfit/autils/keputils.py
src/starfit/autils/loader.py
src/starfit/autils/logged.py
src/starfit/autils/physconst.py
src/starfit/autils/stardb.py
src/starfit/autils/utils.py
src/starfit/autils/uuidtime.py
src/starfit/autils/human/__init__.py
src/starfit/autils/human/byte.py
src/starfit/autils/human/config.py
src/starfit/autils/human/power.py
src/starfit/autils/human/prefix.py
src/starfit/autils/human/range.py
src/starfit/autils/human/template.py
src/starfit/autils/human/time.py
src/starfit/autils/human/unit.py
src/starfit/autils/human/util.py
src/starfit/autils/human/value.py
src/starfit/autils/human/version.py
src/starfit/data/db/.hashlist
src/starfit/data/db/he2sn.HW02.star.el.y.stardb.gz
