Metadata-Version: 2.1
Name: starfit
Version: 0.19.1
Summary: A stellar abundance matching code
Home-page: https://github.com/conradtchan/StarFit
Author: Conrad Chan, Alexander Heger
Author-email: ctchan@swin.edu.au, alexander.heger@monash.edu
License: GPLv3
Platform: any
Classifier: Programming Language :: Python
Classifier: Programming Language :: Python :: 3
Classifier: Development Status :: 4 - Beta
Classifier: License :: OSI Approved :: GNU General Public License v3 or later (GPLv3+)
Classifier: Intended Audience :: Science/Research
Classifier: Topic :: Scientific/Engineering :: Astronomy
Classifier: Topic :: Scientific/Engineering :: Physics
Requires-Python: >=3.8
Provides-Extra: testing
License-File: LICENSE
